sklearnplot/__init__.py
sklearnplot/adversial.py
sklearnplot/informed.py
sklearnplot/preprocessing.py
sklearnplot/prolog.py
sklearnplot/search.py
sklearnplot/supervised.py
sklearnplot/wumpus.py
sklearnplot-0.1.0.dist-info/LICENSE
sklearnplot-0.1.0.dist-info/METADATA
sklearnplot-0.1.0.dist-info/WHEEL
sklearnplot-0.1.0.dist-info/top_level.txt
sklearnplot-0.1.0.dist-info/RECORD
